mkdocs_version/__init__.py
mkdocs_version/__version__.py
mkdocs_version/commands.py
mkdocs_version/version.py
mkdocs_version-0.2.0.dist-info/entry_points.txt
mkdocs_version-0.2.0.dist-info/LICENSE
mkdocs_version-0.2.0.dist-info/WHEEL
mkdocs_version-0.2.0.dist-info/METADATA
mkdocs_version-0.2.0.dist-info/RECORD
