Metadata-Version: 2.1
Name: mkdocs-version
Version: 0.2.0
Summary: Simple and easy-to-use mkdocs version based on git tags
Home-page: https://github.com/abersheeran/mkdocs-version
License: Apache-2.0
Author: abersheeran
Author-email: me@abersheeran.com
Requires-Python: >=3.6,<4.0
Classifier: License :: OSI Approved :: Apache Software License
Classifier: Programming Language :: Python :: 3
Classifier: Programming Language :: Python :: 3.6
Classifier: Programming Language :: Python :: 3.7
Classifier: Programming Language :: Python :: 3.8
Classifier: Programming Language :: Python :: 3.9
Requires-Dist: click (>=7.1.2,<8.0.0)
Requires-Dist: cool (>=0.4.0,<0.5.0)
Project-URL: Repository, https://github.com/abersheeran/mkdocs-version
